odoo10_addon_l10n_es_aeat_vat_prorrate-10.0.1.0.0-py2.7-nspkg.pth
odoo/addons/l10n_es_aeat_vat_prorrate/README.rst
odoo/addons/l10n_es_aeat_vat_prorrate/__init__.py
odoo/addons/l10n_es_aeat_vat_prorrate/__manifest__.py
odoo/addons/l10n_es_aeat_vat_prorrate/data/aeat_export_mod303_data.xml
odoo/addons/l10n_es_aeat_vat_prorrate/data/tax_code_map_mod303_data.xml
odoo/addons/l10n_es_aeat_vat_prorrate/i18n/bg.po
odoo/addons/l10n_es_aeat_vat_prorrate/i18n/ca.po
odoo/addons/l10n_es_aeat_vat_prorrate/i18n/ca_ES.po
odoo/addons/l10n_es_aeat_vat_prorrate/i18n/cs.po
odoo/addons/l10n_es_aeat_vat_prorrate/i18n/es.po
odoo/addons/l10n_es_aeat_vat_prorrate/i18n/es_CO.po
odoo/addons/l10n_es_aeat_vat_prorrate/i18n/es_CR.po
odoo/addons/l10n_es_aeat_vat_prorrate/i18n/eu.po
odoo/addons/l10n_es_aeat_vat_prorrate/i18n/fr.po
odoo/addons/l10n_es_aeat_vat_prorrate/i18n/gl.po
odoo/addons/l10n_es_aeat_vat_prorrate/i18n/hr.po
odoo/addons/l10n_es_aeat_vat_prorrate/i18n/nl.po
odoo/addons/l10n_es_aeat_vat_prorrate/i18n/pl.po
odoo/addons/l10n_es_aeat_vat_prorrate/i18n/pt.po
odoo/addons/l10n_es_aeat_vat_prorrate/i18n/pt_BR.po
odoo/addons/l10n_es_aeat_vat_prorrate/i18n/ru.po
odoo/addons/l10n_es_aeat_vat_prorrate/i18n/sl.po
odoo/addons/l10n_es_aeat_vat_prorrate/i18n/sv.po
odoo/addons/l10n_es_aeat_vat_prorrate/i18n/tr.po
odoo/addons/l10n_es_aeat_vat_prorrate/i18n/vi.po
odoo/addons/l10n_es_aeat_vat_prorrate/models/__init__.py
odoo/addons/l10n_es_aeat_vat_prorrate/models/mod303.py
odoo/addons/l10n_es_aeat_vat_prorrate/static/description/icon.png
odoo/addons/l10n_es_aeat_vat_prorrate/static/description/icon_source.svg
odoo/addons/l10n_es_aeat_vat_prorrate/tests/__init__.py
odoo/addons/l10n_es_aeat_vat_prorrate/tests/test_l10n_es_vat_prorrate.py
odoo/addons/l10n_es_aeat_vat_prorrate/views/mod303_view.xml
odoo/addons/l10n_es_aeat_vat_prorrate/wizard/__init__.py
odoo/addons/l10n_es_aeat_vat_prorrate/wizard/l10n_es_aeat_compute_vat_prorrate.py
odoo10_addon_l10n_es_aeat_vat_prorrate-10.0.1.0.0.dist-info/DESCRIPTION.rst
odoo10_addon_l10n_es_aeat_vat_prorrate-10.0.1.0.0.dist-info/METADATA
odoo10_addon_l10n_es_aeat_vat_prorrate-10.0.1.0.0.dist-info/RECORD
odoo10_addon_l10n_es_aeat_vat_prorrate-10.0.1.0.0.dist-info/WHEEL
odoo10_addon_l10n_es_aeat_vat_prorrate-10.0.1.0.0.dist-info/metadata.json
odoo10_addon_l10n_es_aeat_vat_prorrate-10.0.1.0.0.dist-info/namespace_packages.txt
odoo10_addon_l10n_es_aeat_vat_prorrate-10.0.1.0.0.dist-info/top_level.txt
